neo_fairy_client/__init__.py
neo_fairy_client/rpc/__init__.py
neo_fairy_client/rpc/fairy_client.py
neo_fairy_client/utils/WitnessRule.py
neo_fairy_client/utils/__init__.py
neo_fairy_client/utils/interpreters.py
neo_fairy_client/utils/misc.py
neo_fairy_client/utils/oracle.py
neo_fairy_client/utils/timers.py
neo_fairy_client/utils/types.py
neo_fairy_client/websocket/__init__.py
neo_fairy_client/websocket/fairy_websocket.py
neo_fairy_client-3.7.5.24.dist-info/LICENSE
neo_fairy_client-3.7.5.24.dist-info/METADATA
neo_fairy_client-3.7.5.24.dist-info/WHEEL
neo_fairy_client-3.7.5.24.dist-info/top_level.txt
neo_fairy_client-3.7.5.24.dist-info/RECORD
