Metadata-Version: 2.2
Name: neo-fairy-client
Version: 3.7.5.24
Summary: Test & debug your Neo3 smart contracts
Home-page: https://github.com/Hecate2/neo-fairy-client
Author: Hecate2
Author-email: hecate2@qq.com
Classifier: Programming Language :: Python :: 3
Classifier: License :: OSI Approved :: MIT License
Classifier: Operating System :: OS Independent
Requires-Python: >=3.8
License-File: LICENSE
Requires-Dist: requests>=2.31.0
Dynamic: author
Dynamic: author-email
Dynamic: classifier
Dynamic: description
Dynamic: description-content-type
Dynamic: home-page
Dynamic: requires-dist
Dynamic: requires-python
Dynamic: summary
